{
	"total": 2180,
	"rows": [{
		"SBBH": "68990000027",
		"SBMC": "空气压缩机",
		"SBXH": "",
		"SBXLH": "",
		"SYKS": "0001",
		"KJKM": "689900",
		"KJKMMC": "其它医疗器械",
		"SYKSMC": "皮肤科",
		"GRRQ": null,
		"QYRQ": "2018-01-10",
		"SBZT": "1",
		"WXLXR": "",
		"WXLXRMC": "888888  ",
		"WXDH": "",
		"WXGS": "",
		"WXGSMC": "",
		"ZZRQ": "2018-01-17",
		"SBCJ": "",
		"SBCJMC": "",
		"WXR": "888888  ",
		"WXPHONE": "",
		"ZJQD": 388.0000,
		"CBRQ": null
	}, {
		"SBBH": "68990000023",
		"SBMC": "脐带护理模拟人（女）",
		"SBXH": "EH1022",
		"SBXLH": "68990000023",
		"SYKS": "0048",
		"KJKM": "689900",
		"KJKMMC": "其它医疗器械",
		"SYKSMC": "医务科",
		"GRRQ": "2017-06-16",
		"QYRQ": "2017-06-16",
		"SBZT": "1",
		"WXLXR": "",
		"WXLXRMC": "",
		"WXDH": "",
		"WXGS": "",
		"WXGSMC": "",
		"ZZRQ": "",
		"SBCJ": "",
		"SBCJMC": "",
		"WXR": "",
		"WXPHONE": "",
		"ZJQD": 800.0000,
		"CBRQ": null
	}, {
		"SBBH": "68990000021",
		"SBMC": "内镜存储柜",
		"SBXH": "DK91-A-2[202]",
		"SBXLH": "XHNJ005",
		"SYKS": "0011",
		"KJKM": "689900",
		"KJKMMC": "其它医疗器械",
		"SYKSMC": "胃镜室",
		"GRRQ": "2011-08-25",
		"QYRQ": "2011-08-25",
		"SBZT": "1",
		"WXLXR": "",
		"WXLXRMC": "",
		"WXDH": "",
		"WXGS": "",
		"WXGSMC": "",
		"ZZRQ": "",
		"SBCJ": "",
		"SBCJMC": "",
		"WXR": "",
		"WXPHONE": "",
		"ZJQD": 39800.0000,
		"CBRQ": null
	}, {
		"SBBH": "68990000020",
		"SBMC": "肋木",
		"SBXH": "RL-QS-05[347]",
		"SBXLH": "68990000020",
		"SYKS": "0045",
		"KJKM": "689900",
		"KJKMMC": "其它医疗器械",
		"SYKSMC": "中医康复科病区",
		"GRRQ": "2014-10-31",
		"QYRQ": "2014-10-31",
		"SBZT": "1",
		"WXLXR": "",
		"WXLXRMC": "",
		"WXDH": "",
		"WXGS": "",
		"WXGSMC": "",
		"ZZRQ": "",
		"SBCJ": "",
		"SBCJMC": "",
		"WXR": "",
		"WXPHONE": "",
		"ZJQD": 1500.0000,
		"CBRQ": null
	}, {
		"SBBH": "68990000019",
		"SBMC": "空气压缩机",
		"SBXH": "[172]",
		"SBXLH": "710512",
		"SYKS": "0010",
		"KJKM": "689900",
		"KJKMMC": "其它医疗器械",
		"SYKSMC": "口腔科",
		"GRRQ": "2011-03-20",
		"QYRQ": "2011-03-20",
		"SBZT": "1",
		"WXLXR": "",
		"WXLXRMC": "",
		"WXDH": "",
		"WXGS": "",
		"WXGSMC": "",
		"ZZRQ": "",
		"SBCJ": "",
		"SBCJMC": "",
		"WXR": "",
		"WXPHONE": "",
		"ZJQD": 9500.0000,
		"CBRQ": null
	}, {
		"SBBH": "68990000018",
		"SBMC": "空气压缩机",
		"SBXH": "[172]",
		"SBXLH": "710468",
		"SYKS": "0010",
		"KJKM": "689900",
		"KJKMMC": "其它医疗器械",
		"SYKSMC": "口腔科",
		"GRRQ": "2011-03-20",
		"QYRQ": "2011-03-20",
		"SBZT": "1",
		"WXLXR": "",
		"WXLXRMC": "",
		"WXDH": "",
		"WXGS": "",
		"WXGSMC": "",
		"ZZRQ": "",
		"SBCJ": "",
		"SBCJMC": "",
		"WXR": "",
		"WXPHONE": "",
		"ZJQD": 9500.0000,
		"CBRQ": null
	}, {
		"SBBH": "68990000017",
		"SBMC": "空气压缩机",
		"SBXH": "LK",
		"SBXLH": "68990000017",
		"SYKS": "0032",
		"KJKM": "689900",
		"KJKMMC": "其它医疗器械",
		"SYKSMC": "供应室",
		"GRRQ": "2013-08-31",
		"QYRQ": "2013-08-31",
		"SBZT": "1",
		"WXLXR": "",
		"WXLXRMC": "",
		"WXDH": "",
		"WXGS": "",
		"WXGSMC": "",
		"ZZRQ": "",
		"SBCJ": "",
		"SBCJMC": "",
		"WXR": "",
		"WXPHONE": "",
		"ZJQD": 9500.0000,
		"CBRQ": null
	}, {
		"SBBH": "68990000016",
		"SBMC": "空气压缩机",
		"SBXH": "[121]",
		"SBXLH": "638026",
		"SYKS": "0010",
		"KJKM": "689900",
		"KJKMMC": "其它医疗器械",
		"SYKSMC": "口腔科",
		"GRRQ": "2008-09-22",
		"QYRQ": "2008-09-22",
		"SBZT": "1",
		"WXLXR": "",
		"WXLXRMC": "",
		"WXDH": "",
		"WXGS": "",
		"WXGSMC": "",
		"ZZRQ": "",
		"SBCJ": "",
		"SBCJMC": "",
		"WXR": "",
		"WXPHONE": "",
		"ZJQD": 24600.0000,
		"CBRQ": null
	}, {
		"SBBH": "68990000015",
		"SBMC": "空气压缩机",
		"SBXH": "[121]",
		"SBXLH": "61178",
		"SYKS": "0010",
		"KJKM": "689900",
		"KJKMMC": "其它医疗器械",
		"SYKSMC": "口腔科",
		"GRRQ": "2008-09-22",
		"QYRQ": "2008-09-22",
		"SBZT": "1",
		"WXLXR": "",
		"WXLXRMC": "",
		"WXDH": "",
		"WXGS": "",
		"WXGSMC": "",
		"ZZRQ": "",
		"SBCJ": "",
		"SBCJMC": "",
		"WXR": "",
		"WXPHONE": "",
		"ZJQD": 24600.0000,
		"CBRQ": null
	}, {
		"SBBH": "68990000014",
		"SBMC": "净化工作台",
		"SBXH": "VS-840-1[311]",
		"SBXLH": "13045",
		"SYKS": "0012",
		"KJKM": "689900",
		"KJKMMC": "其它医疗器械",
		"SYKSMC": "检验科办公室",
		"GRRQ": "2013-11-30",
		"QYRQ": "2013-11-30",
		"SBZT": "1",
		"WXLXR": "",
		"WXLXRMC": "",
		"WXDH": "",
		"WXGS": "",
		"WXGSMC": "",
		"ZZRQ": "",
		"SBCJ": "",
		"SBCJMC": "",
		"WXR": "",
		"WXPHONE": "",
		"ZJQD": 12000.0000,
		"CBRQ": null
	}]
}
